uom/__init__.py
uom/cmd_line.py
uom/unit_alias.py
uom/uom.csv
uom/uom.py
uom/uomdata.py
uom-0.6.3.dist-info/LICENSE.md
uom-0.6.3.dist-info/METADATA
uom-0.6.3.dist-info/WHEEL
uom-0.6.3.dist-info/entry_points.txt
uom-0.6.3.dist-info/top_level.txt
uom-0.6.3.dist-info/RECORD
