Metadata-Version: 2.1
Name: uom
Version: 0.6.3
Summary: Unit of Measure conversion tool
Home-page: http://github.com/schlumberger/UOM
Author: Velizar VESSELINOV
Author-email: vvesselinov@slb.com
License: BSD 2-Clause “Simplified” License
Keywords: uom unit measurement measure Energistics oilfield
Classifier: Development Status :: 5 - Production/Stable
Classifier: Environment :: Console
Classifier: Intended Audience :: Customer Service
Classifier: Intended Audience :: Developers
Classifier: Intended Audience :: Science/Research
Classifier: License :: OSI Approved :: BSD License
Classifier: Programming Language :: Python :: 3.6
Classifier: Programming Language :: Python :: 3.7
Classifier: Programming Language :: Python :: 3.8
Classifier: Programming Language :: Python :: 3.9
Classifier: Programming Language :: Python :: 3.10
Classifier: Topic :: Scientific/Engineering
Classifier: Topic :: Scientific/Engineering :: Information Analysis
Requires-Python: >=3.6
License-File: LICENSE.md
Requires-Dist: pandas
